.coveragerc
.gitignore
.mailmap
.travis.yml
CHANGELOG
CONTRIBUTING.txt
LICENSE.txt
MANIFEST.in
README.md
setup.py
doc/Makefile
doc/listmissing.py
doc/make.bat
doc/extensions/qt_doc.py
doc/source/3dgraphics.rst
doc/source/apireference.rst
doc/source/colormap.rst
doc/source/conf.py
doc/source/config_options.rst
doc/source/exporting.rst
doc/source/functions.rst
doc/source/graphicswindow.rst
doc/source/how_to_use.rst
doc/source/images.rst
doc/source/index.rst
doc/source/installation.rst
doc/source/internals.rst
doc/source/introduction.rst
doc/source/mouse_interaction.rst
doc/source/plotting.rst
doc/source/prototyping.rst
doc/source/qtcrashcourse.rst
doc/source/region_of_interest.rst
doc/source/style.rst
doc/source/3dgraphics/glaxisitem.rst
doc/source/3dgraphics/glgraphicsitem.rst
doc/source/3dgraphics/glgriditem.rst
doc/source/3dgraphics/glimageitem.rst
doc/source/3dgraphics/gllineplotitem.rst
doc/source/3dgraphics/glmeshitem.rst
doc/source/3dgraphics/glscatterplotitem.rst
doc/source/3dgraphics/glsurfaceplotitem.rst
doc/source/3dgraphics/glviewwidget.rst
doc/source/3dgraphics/glvolumeitem.rst
doc/source/3dgraphics/index.rst
doc/source/3dgraphics/meshdata.rst
doc/source/flowchart/flowchart.rst
doc/source/flowchart/index.rst
doc/source/flowchart/node.rst
doc/source/flowchart/terminal.rst
doc/source/graphicsItems/arrowitem.rst
doc/source/graphicsItems/axisitem.rst
doc/source/graphicsItems/buttonitem.rst
doc/source/graphicsItems/curvearrow.rst
doc/source/graphicsItems/curvepoint.rst
doc/source/graphicsItems/errorbaritem.rst
doc/source/graphicsItems/fillbetweenitem.rst
doc/source/graphicsItems/gradienteditoritem.rst
doc/source/graphicsItems/gradientlegend.rst
doc/source/graphicsItems/graphicsitem.rst
doc/source/graphicsItems/graphicslayout.rst
doc/source/graphicsItems/graphicsobject.rst
doc/source/graphicsItems/graphicswidget.rst
doc/source/graphicsItems/graphicswidgetanchor.rst
doc/source/graphicsItems/graphitem.rst
doc/source/graphicsItems/griditem.rst
pyqtgraph_for_dubble_bubble.egg-info/PKG-INFO
pyqtgraph_for_dubble_bubble.egg-info/SOURCES.txt
pyqtgraph_for_dubble_bubble.egg-info/dependency_links.txt
pyqtgraph_for_dubble_bubble.egg-info/requires.txt
pyqtgraph_for_dubble_bubble.egg-info/top_level.txt
